CHANGES.txt
CONTRIBUTORS.txt
MANIFEST.in
README.txt
setup.py
collective/__init__.py
collective.allowtypes.egg-info/PKG-INFO
collective.allowtypes.egg-info/SOURCES.txt
collective.allowtypes.egg-info/dependency_links.txt
collective.allowtypes.egg-info/entry_points.txt
collective.allowtypes.egg-info/namespace_packages.txt
collective.allowtypes.egg-info/not-zip-safe
collective.allowtypes.egg-info/paster_plugins.txt
collective.allowtypes.egg-info/requires.txt
collective.allowtypes.egg-info/top_level.txt
collective/allowtypes/CHANGELOG
collective/allowtypes/__init__.py
collective/allowtypes/configure.zcml
collective/allowtypes/setuphandlers.py
collective/allowtypes/version.txt
collective/allowtypes/browser/__init__.py
collective/allowtypes/browser/allowtypes.pt
collective/allowtypes/browser/browser.py
collective/allowtypes/browser/configure.zcml
collective/allowtypes/profiles/default/actionicons.xml
collective/allowtypes/profiles/default/allowtypes.txt
collective/allowtypes/profiles/default/controlpanel.xml
collective/allowtypes/profiles/default/import_steps.xml
collective/allowtypes/profiles/default/metadata.xml
collective/allowtypes/tests/__init__.py
collective/allowtypes/tests/base.py
collective/allowtypes/tests/test_setup.py
collective/allowtypes/tests/test_view.py
docs/HISTORY.txt
docs/INSTALL.txt
docs/LICENSE.GPL
docs/LICENSE.txt