Metadata-Version: 1.0
Name: collective.allowtypes
Version: 0.2
Summary: Set allowed content type for Plone in a n x n Matrix
Home-page: https://svn.plone.org/svn/collective/collective.allowtypes
Author: Ramon Bartl
Author-email: ramon.bartl@inquant.de
License: GPL
Platform: UNKNOWN
Classifier: Framework :: Plone
Classifier: Intended Audience :: Developers
Classifier: Topic :: Software Development :: Libraries :: Python Modules
Classifier: License :: OSI Approved :: GNU General Public License (GPL)
